dsnd_probability_ka_24/Binomialdistribution.py
dsnd_probability_ka_24/Gaussiandistribution.py
dsnd_probability_ka_24/Generaldistribution.py
dsnd_probability_ka_24/__init__.py
dsnd_probability_ka_24-0.1.dist-info/DESCRIPTION.rst
dsnd_probability_ka_24-0.1.dist-info/METADATA
dsnd_probability_ka_24-0.1.dist-info/RECORD
dsnd_probability_ka_24-0.1.dist-info/WHEEL
dsnd_probability_ka_24-0.1.dist-info/metadata.json
dsnd_probability_ka_24-0.1.dist-info/top_level.txt
