Metadata-Version: 2.0
Name: dsnd-probability-ka-24
Version: 0.1
Summary: Gaussian and Binomial distributions
Home-page: UNKNOWN
Author: Kaoutar Qanouni
Author-email: UNKNOWN
License: UNKNOWN
Platform: UNKNOWN
